<annotation>
	<folder>crack roads</folder>
	<filename>c47.jpg</filename>
	<path>G:/crack roads/c47.jpg</path>
	<source>
		<database>Unknown</database>
	</source>
	<size>
		<width>510</width>
		<height>354</height>
		<depth>3</depth>
	</size>
	<segmented>0</segmented>
	<object>
		<name>crack</name>
		<pose>Unspecified</pose>
		<truncated>1</truncated>
		<difficult>0</difficult>
		<bndbox>
			<xmin>123</xmin>
			<ymin>289</ymin>
			<xmax>397</xmax>
			<ymax>354</ymax>
		</bndbox>
	</object>
	<object>
		<name>crack</name>
		<pose>Unspecified</pose>
		<truncated>0</truncated>
		<difficult>0</difficult>
		<bndbox>
			<xmin>206</xmin>
			<ymin>198</ymin>
			<xmax>388</xmax>
			<ymax>262</ymax>
		</bndbox>
	</object>
	<object>
		<name>crack</name>
		<pose>Unspecified</pose>
		<truncated>0</truncated>
		<difficult>0</difficult>
		<bndbox>
			<xmin>164</xmin>
			<ymin>157</ymin>
			<xmax>260</xmax>
			<ymax>188</ymax>
		</bndbox>
	</object>
</annotation>
